nlp_processes/__init__.py
nlp_processes/preprocessing.py
nlp_processes-1.0.dist-info/METADATA
nlp_processes-1.0.dist-info/WHEEL
nlp_processes-1.0.dist-info/top_level.txt
nlp_processes-1.0.dist-info/RECORD
