Metadata-Version: 2.1
Name: nlp-processes
Version: 1.0
Summary: UNKNOWN
Home-page: UNKNOWN
Author: Sina Heydari
Author-email: sinaa.heydari.76@gmail.com
License: UNKNOWN
Platform: UNKNOWN
Classifier: Programming Language :: Python :: 3
Requires-Python: >=3.10, <3.11
Requires-Dist: matplotlib
Requires-Dist: numpy
Requires-Dist: pandas
Requires-Dist: spacy (>=3.0.0)
Requires-Dist: spacy-cleaner
Requires-Dist: tqdm
